README.md
setup.py
urwid_ueberzogen/__init__.py
urwid_ueberzogen.egg-info/PKG-INFO
urwid_ueberzogen.egg-info/SOURCES.txt
urwid_ueberzogen.egg-info/dependency_links.txt
urwid_ueberzogen.egg-info/requires.txt
urwid_ueberzogen.egg-info/top_level.txt